{"1":[{"beverage":"apple","quantity":"6","date":"11/25/2019, 11:16:02 AM"},{"beverage":"orange","quantity":"9","date":"11/25/2019, 11:16:51 AM"},{"beverage":"watermelon","quantity":"2","date":"11/25/2019, 11:17:01 AM"},{"beverage":"watermelon","quantity":"2","date":"11/25/2019, 11:19:51 AM"},{"beverage":"watermelon","quantity":"2","date":"11/25/2019, 3:31:39 PM"}],"2":[{"beverage":"watermelon","quantity":"2","date":"11/25/2019, 11:17:11 AM"},{"beverage":"apple","quantity":"2","date":"11/25/2019, 7:33:39 PM"}],"5":[{"beverage":"apple","quantity":"4","date":"11/25/2019, 11:16:32 AM"},{"beverage":"apple","quantity":"9","date":"11/25/2019, 11:16:38 AM"}]}